<areas><area><id>0</id><title>Sarri</title><position><X>23.72403</X><Y>37.97992</Y></position><zoom>19</zoom><areaConstraintsMin><X>23.72334</X><Y>37.97966</Y></areaConstraintsMin><areaConstraintsMax><X>23.72473</X><Y>37.98019</Y></areaConstraintsMax><viewConstraintsMin><X>23.72231</X><Y>37.97779</Y></viewConstraintsMin><viewConstraintsMax><X>23.72574</X><Y>37.98212</Y></viewConstraintsMax><paths><path><areaId>0</areaId><id>0</id><title>path_0_2021-05-13</title><date>13/5/2021 11:13:05 π.μ.</date><pathPoints><pathPoint><pathId>0</pathId><index>0</index><position><X>23.72402</X><Y>37.97995</Y></position><time>11:13:05.9266460</time></pathPoint><pathPoint><pathId>0</pathId><index>1</index><position><X>23.7242</X><Y>37.97995</Y></position><time>11:13:31.1341546</time></pathPoint><pathPoint><pathId>0</pathId><index>2</index><position><X>23.7244</X><Y>37.97995</Y></position><time>11:13:35.1457574</time></pathPoint></pathPoints></path><path><areaId>0</areaId><id>1</id><title>path_1_2021-05-13</title><date>13/5/2021 12:27:07 μ.μ.</date><pathPoints><pathPoint><pathId>1</pathId><index>0</index><position><X>23.72402</X><Y>37.97995</Y></position><time>12:27:07.0475607</time></pathPoint><pathPoint><pathId>1</pathId><index>1</index><position><X>23.72402</X><Y>37.9798</Y></position><time>12:27:43.1450480</time></pathPoint><pathPoint><pathId>1</pathId><index>2</index><position><X>23.72402</X><Y>37.9797</Y></position><time>12:27:47.0111760</time></pathPoint></pathPoints></path></paths></area></areas>